alpacloud/__init__.py
alpacloud/argocdkit/__main__.py
alpacloud/argocdkit/cmp.py
alpacloud/argocdkit/postrender.py
alpacloud/argocdkit/spec.py
alpacloud.argocdkit-0.1.0.dist-info/METADATA
alpacloud.argocdkit-0.1.0.dist-info/WHEEL
alpacloud.argocdkit-0.1.0.dist-info/namespace_packages.txt
alpacloud.argocdkit-0.1.0.dist-info/top_level.txt
alpacloud.argocdkit-0.1.0.dist-info/RECORD
