Metadata-Version: 2.1
Name: alpacloud.argocdkit
Version: 0.1.0
Summary: A library for modifying Kubernetes manifests and other json-like objects.
Author: Daniel Goldman
License: Round Robin 2.0.0
Classifier: Development Status :: 3 - Alpha
Classifier: Programming Language :: Python :: 3.10
Classifier: Programming Language :: Python :: 3.11
Classifier: Programming Language :: Python :: 3.12
Classifier: Programming Language :: Python :: 3.13
Classifier: Topic :: Utilities
Classifier: Topic :: System :: Systems Administration
Requires-Python: >=3.11
Requires-Dist: PyYAML>=6.0
Requires-Dist: alpacloud.lens==0.1.0
Requires-Dist: exceptiongroup~=1.3.0
Requires-Dist: mypy~=1.16.1
Requires-Dist: pydantic-settings~=2.10.1
Requires-Dist: pydantic~=2.11.7
Requires-Dist: sh~=2.2.2
Requires-Dist: types-PyYAML
Requires-Dist: types-requests
